AUTHORS.rst
CONTRIBUTING.rst
HISTORY.rst
LICENSE
MANIFEST.in
README.rst
setup.cfg
setup.py
bin/git-lint-style
bin/pre-commit
docs/Makefile
docs/arguments.rst
docs/authors.rst
docs/conf.py
docs/contributing.rst
docs/git_lint.rst
docs/history.rst
docs/index.rst
docs/installation.rst
docs/make.bat
docs/manual.rst
docs/modules.rst
docs/readme.rst
docs/strategies.rst
docs/usage.rst
docs/_build/html/_static/ajax-loader.gif
docs/_build/html/_static/comment-bright.png
docs/_build/html/_static/comment-close.png
docs/_build/html/_static/comment.png
docs/_build/html/_static/down-pressed.png
docs/_build/html/_static/down.png
docs/_build/html/_static/file.png
docs/_build/html/_static/minus.png
docs/_build/html/_static/plus.png
docs/_build/html/_static/up-pressed.png
docs/_build/html/_static/up.png
docs/_build/man/git-lint.1
git_lint/__init__.py
git_lint/__main__.py
git_lint/git_lint.py
git_lint/option_handler.py
git_lint/options.py
git_lint/reporters.py
git_linter.egg-info/PKG-INFO
git_linter.egg-info/SOURCES.txt
git_linter.egg-info/dependency_links.txt
git_linter.egg-info/entry_points.txt
git_linter.egg-info/not-zip-safe
git_linter.egg-info/top_level.txt
tests/__init__.py
tests/test_git_lint.py