Metadata-Version: 1.1
Name: git-linter
Version: 0.0.7
Summary: A git command to lint everything in your workspace (or stage) that was changed since the last commit.
Home-page: https://github.com/elfsternberg/git_linter
Author: Kenneth M. "Elf" Sternberg
Author-email: elf.sternberg@gmail.com
License: MIT
Keywords: git lint style syntaxt development
Platform: UNKNOWN
Classifier: Development Status :: 2 - Pre-Alpha
Classifier: Intended Audience :: Developers
Classifier: License :: OSI Approved :: ISC License (ISCL)
Classifier: Natural Language :: English
Classifier: Programming Language :: Python :: 2
Classifier: Programming Language :: Python :: 2.7
Classifier: Programming Language :: Python :: 3
Classifier: Programming Language :: Python :: 3.3
Classifier: Programming Language :: Python :: 3.4
Classifier: Programming Language :: Python :: 3.5
